dataform_checklist/__init__.py
dataform_checklist/cli.py
dataform_checklist/excel_utils.py
dataform_checklist/exporter.py
dataform_checklist/file_utils.py
dataform_checklist/inventory_utils.py
dataform_checklist/models.py
dataform_checklist/template/PTTEP_Dataform_Deployment_Checklist_template_v1.00.00.xlsx
dataform_checklist-1.3.1.dist-info/licenses/LICENSE
dataform_checklist-1.3.1.dist-info/METADATA
dataform_checklist-1.3.1.dist-info/WHEEL
dataform_checklist-1.3.1.dist-info/entry_points.txt
dataform_checklist-1.3.1.dist-info/top_level.txt
dataform_checklist-1.3.1.dist-info/RECORD
