Metadata-Version: 2.4
Name: dataform-checklist
Version: 1.3.1
Summary: Generate Excel deployment checklists from Dataform repositories
Home-page: https://github.com/pttep/dataform-checklist
Author: PTTEP Data Engineering Team
Author-email: PTTEP Data Engineering Team <data-engineering@pttep.com>
License: MIT
Project-URL: Homepage, https://github.com/OshigeAkito/dataform-checklist-package
Project-URL: Bug Reports, https://github.com/OshigeAkito/dataform-checklist-package/issues
Project-URL: Source, https://github.com/OshigeAkito/dataform-checklist-package
Project-URL: Documentation, https://github.com/OshigeAkito/dataform-checklist-package#readme
Keywords: dataform,deployment,checklist,excel,bigquery
Classifier: Development Status :: 4 - Beta
Classifier: Intended Audience :: Developers
Classifier: Topic :: Software Development :: Build Tools
Classifier: Programming Language :: Python :: 3
Classifier: Programming Language :: Python :: 3.7
Classifier: Programming Language :: Python :: 3.8
Classifier: Programming Language :: Python :: 3.9
Classifier: Programming Language :: Python :: 3.10
Classifier: Programming Language :: Python :: 3.11
Classifier: License :: OSI Approved :: MIT License
Classifier: Operating System :: OS Independent
Requires-Python: >=3.7
License-File: LICENSE
Requires-Dist: pandas>=2.0.0
Requires-Dist: openpyxl>=3.1.0
Dynamic: author
Dynamic: home-page
Dynamic: license-file
Dynamic: requires-python
